Workbook

Sheet README
A1: Renewal Shield — Clause Bank v0.3 (draft)
A3: What this is
A4: Example clauses for the 6 v1 clause types, each in a 'problem' and a 'fine' version. This is the base for the synthetic contracts, the labels and the benchmark.
A6: How to review (your job)
A7: 1. Go through the 'Clause Bank' sheet row by row.
A8: 2. Yellow columns are yours: set 'verified' to yes / no / unsure.
A9: 3. If the wording doesn't sound like a real Dubai contract, rewrite it in 'edited_text'.
A10: 4. Use 'notes' for anything else (wrong label, wrong law ref, idea for a new variant).
A11: 5. Confirm every law_ref against the official text. IMPORTANT: use Law 26/2007 AS AMENDED by Law 33/2008 (the amendment replaced Articles 2, 3, 4, 9, 13, 14, 15, 25, 26, 29, 36). The original 2007 PDF alone is out of date for Art. 9, 13, 14, 25 and 26. Rent caps come from Decree 43/2013 + the DLD rental index.
A13: Column guide
A14: label: problem = should be flagged; fine = should NOT be flagged.
A15: severity: red = likely conflicts with the law · yellow = legal but unfavourable (negotiate) · none = fine.
... A23: Some clauses use placeholders that the generator fills from the contract's own fields so numbers always match: {deposit}, {rent}, {rent_next_year}, {cleaning_fee}. You can use them in edited_text too.

Sheet Summary
A1: category | B1: problem | C1: fine | D1: hard rows | E1: verified yes | F1: verified total | G1: % verified
A2: rent_increase | B2: =COUNTIFS('Clause Bank'!$B$2:$B$61,A2,'Clause Bank'!$C$2:$C$61,"problem") -> 5 | C2: =COUNTIFS('Clause Bank'!$B$2:$B$61,A2,'Clause Bank'!$C$2:$C$61,"fine") -> 5 | D2: =COUNTIFS('Clause Bank'!$B$2:$B$61,A2,'Clause Bank'!$E$2:$E$61,"hard") -> 4 | E2: =COUNTIFS('Clause Bank'!$B$2:$B$61,A2,'Clause Bank'!$I$2:$I$61,"yes") -> 0 | F2: =B2+C2 -> 10 | G2: =IF(F2=0,0,E2/F2) -> 0
A3: notice_period | B3: =COUNTIFS('Clause Bank'!$B$2:$B$61,A3,'Clause Bank'!$C$2:$C$61,"problem") -> 5 | C3: =COUNTIFS('Clause Bank'!$B$2:$B$61,A3,'Clause Bank'!$C$2:$C$61,"fine") -> 5 | D3: =COUNTIFS('Clause Bank'!$B$2:$B$61,A3,'Clause Bank'!$E$2:$E$61,"hard") -> 4 | E3: =COUNTIFS('Clause Bank'!$B$2:$B$61,A3,'Clause Bank'!$I$2:$I$61,"yes") -> 0 | F3: =B3+C3 -> 10 | G3: =IF(F3=0,0,E3/F3) -> 0
A4: landlord_termination | B4: =COUNTIFS('Clause Bank'!$B$2:$B$61,A4,'Clause Bank'!$C$2:$C$61,"problem") -> 5 | C4: =COUNTIFS('Clause Bank'!$B$2:$B$61,A4,'Clause Bank'!$C$2:$C$61,"fine") -> 5 | D4: =COUNTIFS('Clause Bank'!$B$2:$B$61,A4,'Clause Bank'!$E$2:$E$61,"hard") -> 4 | E4: =COUNTIFS('Clause Bank'!$B$2:$B$61,A4,'Clause Bank'!$I$2:$I$61,"yes") -> 0 | F4: =B4+C4 -> 10 | G4: =IF(F4=0,0,E4/F4) -> 0
A5: early_termination | B5: =COUNTIFS('Clause Bank'!$B$2:$B$61,A5,'Clause Bank'!$C$2:$C$61,"problem") -> 5 | C5: =COUNTIFS('Clause Bank'!$B$2:$B$61,A5,'Clause Bank'!$C$2:$C$61,"fine") -> 5 | D5: =COUNTIFS('Clause Bank'!$B$2:$B$61,A5,'Clause Bank'!$E$2:$E$61,"hard") -> 4 | E5: =COUNTIFS('Clause Bank'!$B$2:$B$61,A5,'Clause Bank'!$I$2:$I$61,"yes") -> 0 | F5: =B5+C5 -> 10 | G5: =IF(F5=0,0,E5/F5) -> 0
A6: maintenance | B6: =COUNTIFS('Clause Bank'!$B$2:$B$61,A6,'Clause Bank'!$C$2:$C$61,"problem") -> 5 | C6: =COUNTIFS('Clause Bank'!$B$2:$B$61,A6,'Clause Bank'!$C$2:$C$61,"fine") -> 5 | D6: =COUNTIFS('Clause Bank'!$B$2:$B$61,A6,'Clause Bank'!$E$2:$E$61,"hard") -> 4 | E6: =COUNTIFS('Clause Bank'!$B$2:$B$61,A6,'Clause Bank'!$I$2:$I$61,"yes") -> 0 | F6: =B6+C6 -> 10 | G6: =IF(F6=0,0,E6/F6) -> 0
A7: deposit | B7: =COUNTIFS('Clause Bank'!$B$2:$B$61,A7,'Clause Bank'!$C$2:$C$61,"problem") -> 5 | C7: =COUNTIFS('Clause Bank'!$B$2:$B$61,A7,'Clause Bank'!$C$2:$C$61,"fine") -> 5 | D7: =COUNTIFS('Clause Bank'!$B$2:$B$61,A7,'Clause Bank'!$E$2:$E$61,"hard") -> 4 | E7: =COUNTIFS('Clause Bank'!$B$2:$B$61,A7,'Clause Bank'!$I$2:$I$61,"yes") -> 0 | F7: =B7+C7 -> 10 | G7: =IF(F7=0,0,E7/F7) -> 0
A8: TOTAL | B8: =SUM(B2:B7) -> 30 | C8: =SUM(C2:C7) -> 30 | D8: =SUM(D2:D7) -> 24 | E8: =SUM(E2:E7) -> 0 | F8: =SUM(F2:F7) -> 60 | G8: =IF(F8=0,0,E8/F8) -> 0

Sheet Categories
A1: category | B1: name | C1: what to flag | D1: law_ref | E1: default severity
A2: rent_increase | B2: Fixed rent increase on renewal | C2: Clause sets a rent increase on renewal (a fixed % or amount, or 'at landlord's discretion') instead of following the official rental index. | D2: Art. 9 (as amended by Law 33/2008); Decree 43/2013; DLD Smart Rental Index | E2: red
A3: notice_period | B3: Short notice to change rent/terms | C3: Landlord can change the rent or other terms at renewal with less than 90 days' notice. Art. 14 allows the parties to agree a different period, so a short agreed period is yellow (negotiate); red only when there is effectively no notice at all. | D3: Art. 14 (90 days unless otherwise agreed by the parties) | E3: yellow/red
A4: landlord_termination | B4: Landlord can end the lease too easily | C4: Landlord can terminate during the term, or refuse renewal / evict at expiry, without the legal grounds and 12 months' notice via notary public or registered mail. | D4: Art. 25 (as amended by Law 33/2008) | E4: red
A5: early_termination | B5: Early termination penalty | C5: What the tenant pays to leave before the end of the term. Not fixed by the law, so it's a negotiation point. Flag if unusually high. | D5: Art. 7 (no unilateral termination during the term; early exit only by mutual consent/contract terms) | E5: yellow
A6: maintenance | B6: Maintenance pushed onto tenant | C6: Default is that the landlord handles maintenance and repairs, but the parties can agree otherwise. Flag clauses that push major/structural repairs onto the tenant. | D6: Art. 16 | E6: yellow
A7: deposit | B7: Deposit deductions / non-refundable deposit | C7: Deposit is non-refundable, or the landlord can deduct at sole discretion without proof, or no refund timeline. | D7: Art. 20 (deposit refunded, or remainder, on expiry); Art. 21 (ordinary wear and tear excepted) | E7: red/yellow

Sheet Clause Bank
A1: id | B1: category | C1: label | D1: severity | E1: difficulty | F1: clause_text | G1: why | H1: law_ref | I1: verified | J1: edited_text | K1: notes
A2: RI-P01 | B2: rent_increase | C2: problem | D2: red | E2: easy | F2: Upon renewal of this contract, the annual rent shall automatically increase by ten percent (10%) of the current rent. | G2: Fixed 10% increase regardless of the rental index. | H2: Art. 9 (as amended by Law 33/2008); Decree 43/2013; DLD Smart Rental Index
A3: RI-P02 | B3: rent_increase | C3: problem | D3: red | E3: easy | F3: The Landlord reserves the right to increase the rent at each renewal at his sole discretion. | G3: Increase left entirely to landlord, ignores the index cap. | H3: Art. 9 (as amended by Law 33/2008); Decree 43/2013; DLD Smart Rental Index
A4: RI-P03 | B4: rent_increase | C4: problem | D4: red | E4: easy | F4: The rent for the second year shall be {rent_next_year} and the Tenant hereby agrees to this amount in advance. | G4: Pre-agreed renewal rent that may exceed what the index permits. | H4: Art. 9 (as amended by Law 33/2008); Decree 43/2013; DLD Smart Rental Index
A5: RI-P04 | B5: rent_increase | C5: problem | D5: red | E5: hard | F5: The Tenant acknowledges that market conditions may require a rent adjustment of up to 15% upon renewal, and agrees to accept such adjustment. | G5: Soft wording ('adjustment', 'up to') but still pre-commits the tenant to an increase above the index. | H5: Art. 9 (as amended by Law 33/2008); Decree 43/2013; DLD Smart Rental Index
A6: RI-P05 | B6: rent_increase | C6: problem | D6: red | E6: hard | F6: Any renewal shall be on the Landlord's then-prevailing market rates, which the Tenant shall not dispute. | G6: 'Market rates' + waiver of the right to dispute bypasses the index. | H6: Art. 9 (as amended by Law 33/2008); Decree 43/2013; DLD Smart Rental Index
A7: RI-F01 | B7: rent_increase | C7: fine | D7: none | E7: easy | F7: Any increase in rent upon renewal shall be in accordance with the rental index issued by the Dubai Land Department / RERA. | G7: Explicitly follows the official index. | H7: Art. 9 (as amended by Law 33/2008); Decree 43/2013; DLD Smart Rental Index
A8: RI-F02 | B8: rent_increase | C8: fine | D8: none | E8: easy | F8: The rent shall remain unchanged for the duration of this contract. | G8: No change during the term. Normal. | H8: Art. 9 (as amended by Law 33/2008); Decree 43/2013; DLD Smart Rental Index
A9: RI-F03 | B9: rent_increase | C9: fine | D9: none | E9: easy | F9: Rent increases, if any, shall be subject to the applicable laws and decrees of the Emirate of Dubai. | G9: Defers to the law. | H9: Art. 9 (as amended by Law 33/2008); Decree 43/2013; DLD Smart Rental Index
A10: RI-F04 | B10: rent_increase | C10: fine | D10: none | E10: hard | F10: The parties may agree on a revised rent upon renewal, provided that any increase does not exceed the limit permitted under the RERA rental index. | G10: Mentions an increase, but capped by the index. Hard negative. | H10: Art. 9 (as amended by Law 33/2008); Decree 43/2013; DLD Smart Rental Index
A11: RI-F05 | B11: rent_increase | C11: fine | D11: none | E11: hard | F11: Should the rental index permit an increase at the time of renewal, the Landlord may apply such increase subject to the notice requirements of the law. | G11: Conditional on index + notice. Hard negative. | H11: Art. 9 (as amended by Law 33/2008); Decree 43/2013; DLD Smart Rental Index
A12: NP-P01 | B12: notice_period | C12: problem | D12: yellow | E12: easy | F12: The Landlord may amend the terms of this contract, including the rent, by giving the Tenant thirty (30) days' notice before expiry. | G12: 30 days is below the 90-day default. Art. 14 allows the parties to agree otherwise, so legal if signed, but unfavourable: negotiate back to 90. | H12: Art. 14 (90 days unless otherwise agreed by the parties)
A13: NP-P02 | B13: notice_period | C13: problem | D13: yellow | E13: easy | F13: Any change to the rent will be communicated to the Tenant one (1) month before the end of the contract. | G13: One month is below the 90-day default; an agreed shorter period is allowed by Art. 14 but bad for the tenant: negotiate. | H13: Art. 14 (90 days unless otherwise agreed by the parties)
... A61: DE-F05 | B61: deposit | C61: fine | D61: none | E61: hard | F61: Normal wear and tear shall not be deducted from the security deposit. | G61: Explicitly protects the tenant. Hard negative. | H61: Art. 20 (deposit refunded, or remainder, on expiry); Art. 21 (ordinary wear and tear excepted)
